Workbook

Sheet WBS
A1: Code | B1: Task Name | C1: Specification - what to do | D1: Category | E1: Owner (lead) | F1: Support | G1: Typology | H1: Priority | I1: Stage | J1: Predecessors | K1: Effort (person-days) | L1: Start | M1: Finish | N1: Span (cal. days) | O1: Day # from start | P1: Notes / watch-outs | S1: PROJECT START (edit to re-baseline)
A2: PF-01 | B2: Close open questions | C2: Get written answers from the organisers: (1) motor/driver/encoder quantities per team, (2) servo intent - brake, leg or other, (3) 1N5819 intent - power-ORing or flyback, (4) is frame material supplied or do we source it, (5) laser/waterjet/lathe access, (6) is the 150 mm cube dimension locked or free, (7) bench PSU availability. | D2: Formulation & Docs | E2: Dejan | F2: Pablo | G2: Management | H2: P0 | I2: S0 | K2: 0.5 | L2: 46226 | M2: 46226 | N2: =IF(L2="","",M2-L2+1) -> 1 | O2: =IF(L2="","",L2-$S$2+1) -> 1 | P2: Highest-leverage task in the plan - it is what unblocks the MF-01 order | S2: 46226
A3: PF-02 | B3: Problem statement & narrative | C3: Write the problem statement and lock the ADCS application framing: momentum-exchange actuation, reaction wheels as the standard spacecraft attitude actuator, Hayabusa2 MINERVA-II / MASCOT hopping as the low-gravity mobility precedent. One paragraph that every other section refers back to. | D3: Formulation & Docs | E3: Dejan | G3: Management | H3: P0 | I3: S0 | K3: 0.5 | L3: 46226 | M3: 46226 | N3: =IF(L3="","",M3-L3+1) -> 1 | O3: =IF(L3="","",L3-$S$2+1) -> 1 | S3: PROJECT END
A4: PF-03 | B4: Scope & requirements | C4: Define what is in and out of scope. Build the requirements table split into Functional (F), Performance (P) and Design constraint (D), each with an ID, a statement and a verification method. | D4: Formulation & Docs | E4: Dejan | F4: Pablo | G4: Analysis | H4: P0 | I4: S0 | J4: PF-02 | K4: 1 | L4: 46227 | M4: 46227 | N4: =IF(L4="","",M4-L4+1) -> 1 | O4: =IF(L4="","",L4-$S$2+1) -> 2 | S4: 46253
A5: PF-04 | B5: Milestones & staging | C5: Define the three prototype stages (S1 1-DoF rig, S2 3D cube, S3 jump) and write a quantitative, binary acceptance criterion for each gate - e.g. 'balances >=60 s and recovers from a finger poke', not 'works well'. | D5: Formulation & Docs | E5: Dejan | G5: Management | H5: P0 | I5: S0 | J5: PF-03 | K5: 0.5 | L5: 46228 | M5: 46228 | N5: =IF(L5="","",M5-L5+1) -> 1 | O5: =IF(L5="","",L5-$S$2+1) -> 3 | S5: Total effort (person-days)
A6: PF-05 | B6: Roles & RACI | C6: Assign a named owner per workstream (control, CAD, manufacturing, documentation) and per TDD section. Produce a one-page RACI so nobody is waiting on an unassigned task. | D6: Formulation & Docs | E6: Dejan | G6: Management | H6: P0 | I6: S0 | K6: 0.25 | L6: 46226 | M6: 46226 | N6: =IF(L6="","",M6-L6+1) -> 1 | O6: =IF(L6="","",L6-$S$2+1) -> 1 | S6: =SUM(K2:K95) -> 95
A7: PF-06 | B7: EoM - 1-DoF pendulum | C7: Derive the equations of motion of the reaction-wheel inverted pendulum by the Lagrangian method. Four states: body angle, body rate, wheel angle, wheel rate. Input = motor torque. Include viscous friction terms. | D7: Formulation & Docs | E7: Dejan | F7: Andrea | G7: Analysis | H7: P0 | I7: S1 | K7: 1 | L7: 46227 | M7: 46228 | N7: =IF(L7="","",M7-L7+1) -> 2 | O7: =IF(L7="","",L7-$S$2+1) -> 2 | S7: P0 effort (person-days)
A8: PF-07 | B8: EoM - 3D cube | C8: Derive the 3D equations of motion for the cube with three orthogonal wheels, for both the edge pivot and the corner pivot. Define body and inertial frames, the attitude parameterisation, and the coupled wheel/body angular momentum terms. | D8: Formulation & Docs | E8: Dejan | F8: Andrea | G8: Analysis | H8: P0 | I8: S2 | J8: PF-06 | K8: 2 | L8: 46230 | M8: 46231 | N8: =IF(L8="","",M8-L8+1) -> 2 | O8: =IF(L8="","",L8-$S$2+1) -> 5 | S8: =SUMIF(H2:H95,"P0",K2:K95) -> 69
A9: PF-08 | B9: Linearisation & controllability | C9: Identify the equilibria (edge and corner), linearise about each, and check controllability and observability of the resulting linear systems. Confirm the corner case is fully unstable with coupled axes. | D9: Formulation & Docs | E9: Dejan | F9: Andrea | G9: Analysis | H9: P0 | I9: S2 | J9: PF-07 | K9: 1 | L9: 46232 | M9: 46232 | N9: =IF(L9="","",M9-L9+1) -> 1 | O9: =IF(L9="","",L9-$S$2+1) -> 7 | S9: Task count (excl. milestones)
A10: PF-09 | B10: Mass / inertia / CoM budget | C10: Build the mass, inertia and centre-of-mass budget parametrically (symbols, not numbers) so the model stands up before hardware exists. Replace with CAD values at CD-18 and measured values at PF-16. | D10: Formulation & Docs | E10: Dejan | F10: Neisa | G10: Analysis | H10: P0 | I10: S0 | J10: PF-01 | K10: 0.75 | L10: 46228 | M10: 46228 | N10: =IF(L10="","",M10-L10+1) -> 1 | O10: =IF(L10="","",L10-$S$2+1) -> 3 | S10: =COUNTIF(D2:D95,"<>Milestone") -> 84
A11: PF-10 | B11: Jump-up analysis | C11: Energy method for the face-to-edge and edge-to-corner tips: CoM rise, inertia about the contact edge, required body rate, required stored angular momentum under an inelastic-collision model, and hence the minimum wheel inertia. Derive the brake impulse requirement dH/dt. | D11: Formulation & Docs | E11: Dejan | F11: Andrea | G11: Analysis | H11: P0 | I11: S3 | J11: PF-07;PF-09 | K11: 1 | L11: 46233 | M11: 46233 | N11: =IF(L11="","",M11-L11+1) -> 1 | O11: =IF(L11="","",L11-$S$2+1) -> 8 | P11: This is what sizes the wheel - it must be done before CD-02 is frozen
A12: PF-11a | B12: TDD - draft body | C12: EVERY MEMBER WRITES THEIR OWN SECTION, Dejan integrates. Section owners: Introduction, background and ADCS application narrative = Dejan. Project organisation, roles and timeline = Dejan. Scope, use cases and requirements table = Dejan with all leads reviewing. Mathematical modelling = Dejan + Andrea. Control architecture = Nicc + Andrea. Mechanical design intent = Neisa + Suvanna. Electrical design intent, architecture diagram and power budget = Pablo. Testing and validation plan = Nicc. Literature = Suvanna. Placeholder figures are acceptable at this point. | D12: Formulation & Docs | E12: ALL | F12: Dejan integrates - see spec for section owners | G12: Management | H12: P0 | I12: S0 | J12: PF-02;PF-03;PF-04;PF-05;PF-06;PF-09 | K12: 1.5 | L12: 46228 | M12: 46229 | N12: =IF(L12="","",M12-L12+1) -> 2 | O12: =IF(L12="","",L12-$S$2+1) -> 3 | P12: Anti-Parkinson checkpoint: due 26 Jul regardless of the 3 Aug deadline | S12: Yellow cells are inputs. Blank Start/Finish = deliberately unscheduled stretch task (CT-24, CT-25).
A13: PF-11b | B13: TDD - deepen + S1 data | C13: Upgrade the technical sections: full 3D equations of motion, linearisation and controllability argument, jump-up momentum budget, control architecture. Then insert the S1 hardware evidence - rig photos, balance trace, disturbance-recovery plot, and the measured Kt / J_wheel / friction from CT-11. | D13: Formulation & Docs | E13: ALL | F13: Dejan integrates | G13: Management | H13: P0 | I13: S0 | J13: PF-11a;PF-07;PF-08;PF-10;CT-10;CT-11 | K13: 1 | L13: 46235 | M13: 46236 | N13: =IF(L13="","",M13-L13+1) -> 2 | O13: =IF(L13="","",L13-$S$2+1) -> 10 | P13: Tight - consumes CT-10/CT-11 results almost same-day. Pull CT-10 left if you can
A14: PF-11c | B14: TDD - assemble & submit | C14: Final assembly: make every figure presentable, run a full read-through for internal consistency, tighten the application story, format references, submit. | D14: Formulation & Docs | E14: ALL | F14: Dejan integrates | G14: Management | H14: P0 | I14: S0 | J14: PF-11b | K14: 1 | L14: 46237 | M14: 46237 | N14: =IF(L14="","",M14-L14+1) -> 1 | O14: =IF(L14="","",L14-$S$2+1) -> 12 | P14: DELIVERABLE - Monday 3 August
A15: PF-12 | B15: Literature & references | C15: Collect and format the reference set: ETH Cubli (IROS 2012, ECC 2013), One-Wheel Cubli (Mechatronics 2023), CubeSat ADCS design guides, MINERVA-II / MASCOT mission reports, LQR and optimal-control texts. Pull the ETH PDFs for the modelling section. | D15: Formulation & Docs | E15: ALL | F15: Suvanna collates | G15: Management | H15: P1 | I15: S0 | K15: 0.5 | L15: 46228 | M15: 46228 | N15: =IF(L15="","",M15-L15+1) -> 1 | O15: =IF(L15="","",L15-$S$2+1) -> 3
A16: PF-13 | B16: Risk register | C16: Tabulate the risks with trigger, impact, owner and mitigation. Minimum set: rim lead time, rotor unbalance, printed-bracket compliance, 5 V rail brownout, yaw drift, wrong motor quantity. | D16: Formulation & Docs | E16: ALL | F16: Pablo collates | G16: Management | H16: P1 | I16: S0 | J16: PF-04 | K16: 0.5 | L16: 46232 | M16: 46232 | N16: =IF(L16="","",M16-L16+1) -> 1 | O16: =IF(L16="","",L16-$S$2+1) -> 7
A17: PF-14 | B17: Test & validation plan | C17: Define how each milestone is verified and which numbers get reported: pointing accuracy, slew settling time, jitter / pointing stability, disturbance-recovery time. These are the metrics a real ADCS is graded on - use them instead of 'it balances'. | D17: Formulation & Docs | E17: Dejan | F17: Andrea | G17: Analysis | H17: P1 | I17: S0 | J17: PF-04 | K17: 0.5 | L17: 46233 | M17: 46233 | N17: =IF(L17="","",M17-L17+1) -> 1 | O17: =IF(L17="","",L17-$S$2+1) -> 8
A18: PF-15 | B18: System-ID plan | C18: Specify the experiments that will produce the plant parameters: Kt by torque arm or known-inertia spin-up, J_wheel by J=tau/alpha, viscous friction by coast-down, loop latency by step-response timing. | D18: Formulation & Docs | E18: Dejan | F18: Nicc | G18: Analysis | H18: P1 | I18: S1 | J18: PF-06 | K18: 0.5 | L18: 46231 | M18: 46231 | N18: =IF(L18="","",M18-L18+1) -> 1 | O18: =IF(L18="","",L18-$S$2+1) -> 6
A19: PF-16 | B19: Model update - real params | C19: Substitute the measured parameters from CT-11 and the CAD mass properties from CD-18 into the model, then re-run the torque-authority and jump-up sizing calculations with real numbers. | D19: Formulation & Docs | E19: Dejan | F19: Andrea | G19: Analysis | H19: P0 | I19: S2 | J19: CT-11;CD-18 | K19: 0.5 | L19: 46237 | M19: 46238 | N19: =IF(L19="","",M19-L19+1) -> 2 | O19: =IF(L19="","",L19-$S$2+1) -> 12
A20: PF-17a | B20: Progress note #1 | C20: Short written status against the milestone gates, plus an incremental update to the TDD sections affected by that week's results. | D20: Formulation & Docs | E20: ALL | F20: Dejan integrates | G20: Management | H20: P1 | J20: PF-11c | K20: 0.25 | L20: 46243 | M20: 46243 | N20: =IF(L20="","",M20-L20+1) -> 1 | O20: =IF(L20="","",L20-$S$2+1) -> 18
A21: PF-17b | B21: Progress note #2 | C21: Same as PF-17a for the following week. | D21: Formulation & Docs | E21: ALL | F21: Dejan integrates | G21: Management | H21: P1 | J21: PF-17a | K21: 0.25 | L21: 46250 | M21: 46250 | N21: =IF(L21="","",M21-L21+1) -> 1 | O21: =IF(L21="","",L21-$S$2+1) -> 25
A22: PF-18 | B22: Final report (TDD v2) | C22: Extend the TDD into the final deliverable: experimental results and plots for every stage reached, the ADCS metrics table, lessons learned, and an explicit honest statement of what was achieved versus what was scoped. | D22: Formulation & Docs | E22: ALL | F22: Dejan integrates | G22: Management | H22: P0 | J22: CT-19;CT-20;CT-21 | K22: 2.5 | L22: 46249 | M22: 46253 | N22: =IF(L22="","",M22-L22+1) -> 5 | O22: =IF(L22="","",L22-$S$2+1) -> 24 | P22: FINAL DELIVERABLE
A23: PF-19 | B23: Demo video & deck | C23: Film the demonstrations including 240 fps slow-motion of the jump-up, cut a short video, and build the presentation deck around the stabilise > reorient > propel > traverse capability ladder. | D23: Formulation & Docs | E23: ALL | F23: Suvanna edits | G23: Management | H23: P0 | J23: CT-19;CT-21 | K23: 1 | L23: 46251 | M23: 46253 | N23: =IF(L23="","",M23-L23+1) -> 3 | O23: =IF(L23="","",L23-$S$2+1) -> 26
A24: CT-01 | B24: Sim environment + 1-DoF plant | C24: Set up the simulation environment (Python + CasADi, or MATLAB). Implement the PF-06 plant and validate it: with zero input and zero friction, total energy must be conserved. | D24: Control & Software | E24: Andrea | G24: Software | H24: P0 | I24: S1 | J24: PF-06 | K24: 1 | L24: 46226 | M24: 46227 | N24: =IF(L24="","",M24-L24+1) -> 2 | O24: =IF(L24="","",L24-$S$2+1) -> 1
A25: CT-02 | B25: LQR 1-DoF (sim) | C25: Design and tune an LQR about the upright equilibrium in simulation. Sweep robustness against J_wheel error, added loop delay and torque saturation so the gains survive contact with real hardware. | D25: Control & Software | E25: Andrea | F25: Dejan | G25: Software | H25: P0 | I25: S1 | J25: CT-01;PF-08 | K25: 1 | L25: 46229 | M25: 46230 | N25: =IF(L25="","",M25-L25+1) -> 2 | O25: =IF(L25="","",L25-$S$2+1) -> 4
A26: CT-03 | B26: Complementary filter | C26: Implement tilt estimation v1: gravity vector from the accelerometer for low-frequency tilt, gyro integration for high-frequency rate, blended by a complementary filter. Tune the crossover in simulation with injected noise and bias. | D26: Control & Software | E26: Nicc | G26: Software | H26: P0 | I26: S1 | J26: CT-01 | K26: 1 | L26: 46230 | M26: 46231 | N26: =IF(L26="","",M26-L26+1) -> 2 | O26: =IF(L26="","",L26-$S$2+1) -> 5
A27: CT-04 | B27: Firmware architecture | C27: Decide and document the firmware structure: inner/outer loop rates (the 500 vs 1000 Hz decision driven by the BMI270 I2C read cost), task scheduling, state-machine skeleton, logging hooks, and where safety logic lives. | D27: Control & Software | E27: Nicc | F27: Andrea | G27: Software | H27: P0 | I27: S1 | K27: 1 | L27: 46227 | M27: 46228 | N27: =IF(L27="","",M27-L27+1) -> 2 | O27: =IF(L27="","",L27-$S$2+1) -> 2 | P27: The IMU interface decision constrains the whole firmware - make it in week 1
A28: CT-05 | B28: CAN-FD comms layer | C28: Write the Teensy-to-moteus communication layer: transmit torque commands, parse the reply frame for wheel position, velocity, current and temperature. The reply frame IS the wheel-state feedback - no separate wiring. | D28: Control & Software | E28: Nicc | F28: Pablo | G28: Software | H28: P0 | I28: S1 | J28: CT-04;MF-03 | K28: 1.5 | L28: 46230 | M28: 46231 | N28: =IF(L28="","",M28-L28+1) -> 2 | O28: =IF(L28="","",L28-$S$2+1) -> 5
A29: CT-06 | B29: BMI270 driver | C29: Write the IMU driver and resolve the interface question: check whether the breakout exposes SPI pads; if not, use the FIFO plus a data-ready interrupt, or drop the outer loop to 500 Hz. A blocking 400 kHz I2C read costs ~300 us. | D29: Control & Software | E29: Nicc | G29: Software | H29: P0 | I29: S1 | J29: CT-04 | K29: 1 | L29: 46231 | M29: 46232 | N29: =IF(L29="","",M29-L29+1) -> 2 | O29: =IF(L29="","",L29-$S$2+1) -> 6
A30: CT-07 | B30: IMU cal + lever arm | C30: Calibrate gyro bias and accelerometer scale, record the mounting rotation matrix, and implement the lever-arm correction a_meas = g_body + w x (w x r) + alpha x r. The cube rotates about the contact corner, not about the IMU. | D30: Control & Software | E30: Nicc | F30: Andrea | G30: Software | H30: P0 | I30: S1 | J30: CT-06 | K30: 1 | L30: 46232 | M30: 46233 | N30: =IF(L30="","",M30-L30+1) -> 2 | O30: =IF(L30="","",L30-$S$2+1) -> 7 | P30: Skip the lever arm and your tilt estimate is corrupted exactly during fast recovery
A31: CT-08 | B31: Telemetry link | C31: Define the Teensy-to-ESP32 UART protocol, stream state over Wi-Fi, and build a ground-station live plot plus command path for start/stop and gain changes. Treat the link as strictly non-safety-critical. | D31: Control & Software | E31: Nicc | G31: Software | H31: P1 | I31: S1 | J31: CT-04 | K31: 1.5 | L31: 46233 | M31: 46235 | N31: =IF(L31="","",M31-L31+1) -> 3 | O31: =IF(L31="","",L31-$S$2+1) -> 8 | P31: Pays for itself: tune LQR gains in an afternoon instead of a week
A32: CT-09 | B32: Safety layer | C32: Implement the software safety envelope: enable the moteus watchdog, tilt-limit auto-disarm, wheel-speed cap, explicit arm/disarm command, and latching fault states that require a deliberate reset. | D32: Control & Software | E32: Nicc | F32: Andrea | G32: Software | H32: P0 | I32: S1 | J32: CT-05 | K32: 1 | L32: 46233 | M32: 46234 | N32: =IF(L32="","",M32-L32+1) -> 2 | O32: =IF(L32="","",L32-$S$2+1) -> 8
A33: CT-10 | B33: S1 - balance 1-DoF rig | C33: Bring the full chain up on the rig: IMU > Teensy > CAN-FD > moteus > wheel. Port the LQR and estimator to hardware, then tune gains against live telemetry until the pendulum balances and rejects disturbance. | D33: Control & Software | E33: Nicc | F33: Andrea | G33: Verification | H33: P0 | I33: S1 | J33: CT-02;CT-03;CT-07;CT-09;MF-08 | K33: 2 | L33: 46234 | M33: 46236 | N33: =IF(L33="","",M33-L33+1) -> 3 | O33: =IF(L33="","",L33-$S$2+1) -> 9 | P33: STAGE S1 GATE - protect this task at all costs
A34: CT-11 | B34: System ID on rig | C34: Execute the PF-15 experiments on the rig: measure real Kt, wheel inertia by spin-up, viscous friction by coast-down, and end-to-end loop latency. Produce a parameter table that replaces every symbolic value. | D34: Control & Software | E34: Andrea | F34: Nicc | G34: Verification | H34: P0 | I34: S1 | J34: MF-08 | K34: 1 | L34: 46235 | M34: 46236 | N34: =IF(L34="","",M34-L34+1) -> 2 | O34: =IF(L34="","",L34-$S$2+1) -> 10
A35: CT-12 | B35: 3D plant model (sim) | C35: Implement the PF-07 3D model in simulation for both edge and corner pivots, and validate it against the analytical derivation and against conserved quantities. | D35: Control & Software | E35: Andrea | F35: Dejan | G35: Software | H35: P0 | I35: S2 | J35: PF-07;CT-01 | K35: 2 | L35: 46237 | M35: 46238 | N35: =IF(L35="","",M35-L35+1) -> 2 | O35: =IF(L35="","",L35-$S$2+1) -> 12
A36: CT-13 | B36: LQR edge (sim) | C36: Design and tune the LQR for edge balance in simulation, using the CD-18 inertia tensor. Verify torque authority against the recoverable-tilt calculation. | D36: Control & Software | E36: Andrea | G36: Software | H36: P0 | I36: S2 | J36: CT-12;PF-08 | K36: 1 | L36: 46239 | M36: 46239 | N36: =IF(L36="","",M36-L36+1) -> 1 | O36: =IF(L36="","",L36-$S$2+1) -> 14
A37: CT-14 | B37: LQR corner (sim) | C37: Design the fully coupled three-axis LQR for corner balance in simulation. This is the hardest equilibrium - all axes coupled, fully unstable. | D37: Control & Software | E37: Andrea | F37: Dejan | G37: Software | H37: P0 | I37: S2 | J37: CT-13 | K37: 1.5 | L37: 46239 | M37: 46240 | N37: =IF(L37="","",M37-L37+1) -> 2 | O37: =IF(L37="","",L37-$S$2+1) -> 14
A38: CT-15 | B38: EKF / MEKF estimator | C38: Upgrade the estimator to a 3D EKF or multiplicative EKF with gyro bias states. Characterise and document the yaw-drift behaviour: with no magnetometer, absolute heading is unobservable. | D38: Control & Software | E38: Nicc | F38: Andrea | G38: Software | H38: P1 | I38: S2 | J38: CT-07;CT-12 | K38: 2 | L38: 46240 | M38: 46242 | N38: =IF(L38="","",M38-L38+1) -> 3 | O38: =IF(L38="","",L38-$S$2+1) -> 15 | P38: Yaw unobservability is the hook that ties this project to the star-tracker team
A39: CT-16 | B39: Momentum management | C39: Add the outer wheel-speed regulation loop that bleeds stored momentum back toward zero so the wheels do not saturate during long holds. This is the direct analogue of spacecraft momentum desaturation. | D39: Control & Software | E39: Andrea | G39: Software | H39: P1 | I39: S2 | J39: CT-14 | K39: 1 | L39: 46244 | M39: 46244 | N39: =IF(L39="","",M39-L39+1) -> 1 | O39: =IF(L39="","",L39-$S$2+1) -> 19 | P39: The strongest single ADCS talking point in the project
A40: CT-17 | B40: Mode state machine | C40: Implement the mode logic and the guarded transitions between them: idle > arm > edge balance > corner balance > slew > wheel spin-up > jump > catch > safe, with a defined abort path from every state. | D40: Control & Software | E40: Nicc | G40: Software | H40: P0 | I40: S2 | J40: CT-09;CT-04 | K40: 1 | L40: 46241 | M40: 46241 | N40: =IF(L40="","",M40-L40+1) -> 1 | O40: =IF(L40="","",L40-$S$2+1) -> 16
A41: CT-18 | B41: S2a - edge balance | C41: Port the edge controller to the assembled cube and retune against the real inertia, real sensor noise and real actuator saturation. Log the disturbance-recovery response. | D41: Control & Software | E41: Andrea | F41: Nicc | G41: Verification | H41: P0 | I41: S2 | J41: CT-13;CT-15;MF-16 | K41: 2 | L41: 46244 | M41: 46247 | N41: =IF(L41="","",M41-L41+1) -> 4 | O41: =IF(L41="","",L41-$S$2+1) -> 19 | P41: STAGE S2a GATE
A42: CT-19 | B42: S2b - corner balance | C42: Bring up the coupled three-axis controller on the corner equilibrium. Measure and report pointing accuracy and jitter as ADCS metrics rather than a qualitative claim. | D42: Control & Software | E42: Andrea | F42: Nicc | G42: Verification | H42: P0 | I42: S2 | J42: CT-18;CT-14;CT-16 | K42: 2 | L42: 46248 | M42: 46250 | N42: =IF(L42="","",M42-L42+1) -> 3 | O42: =IF(L42="","",L42-$S$2+1) -> 23 | P42: STAGE S2b GATE
A43: CT-20 | B43: S2c - commanded slew | C43: Command a rotation to a specified angle and track it. Report settling time and steady-state error - this is the reference-tracking half of the ADCS story. | D43: Control & Software | E43: Nicc | F43: Andrea | G43: Verification | H43: P1 | I43: S2 | J43: CT-19 | K43: 1.5 | L43: 46249 | M43: 46250 | N43: =IF(L43="","",M43-L43+1) -> 2 | O43: =IF(L43="","",L43-$S$2+1) -> 24
A44: CT-21 | B44: S3a - jump-up | C44: Implement the jump sequence: wheel spin-up profile to target angular momentum, scripted brake release with tuned timing, open loop. Iterate the release timing against slow-motion footage. | D44: Control & Software | E44: Nicc | F44: Andrea, Pablo | G44: Verification | H44: P1 | I44: S3 | J44: CT-17;MF-17 | K44: 1.5 | L44: 46251 | M44: 46252 | N44: =IF(L44="","",M44-L44+1) -> 2 | O44: =IF(L44="","",L44-$S$2+1) -> 26 | P44: STAGE S3 GATE
A45: CT-22 | B45: S3b - catch controller | C45: Add the gain-scheduled transition that catches the cube after the jump and settles it into edge or corner balance rather than letting it fall. | D45: Control & Software | E45: Andrea | F45: Nicc | G45: Verification | H45: P2 | I45: S3 | J45: CT-21;CT-19 | K45: 1.5 | L45: 46252 | M45: 46253 | N45: =IF(L45="","",M45-L45+1) -> 2 | O45: =IF(L45="","",L45-$S$2+1) -> 27 | P45: Only attempt if CT-21 works on Monday the 17th
A46: CT-23 | B46: Log post-processing | C46: Write the scripts that turn raw telemetry logs into the reported metrics and into publication-quality plots for the report and the deck. | D46: Control & Software | E46: Andrea | G46: Software | H46: P1 | J46: CT-08 | K46: 1 | L46: 46240 | M46: 46241 | N46: =IF(L46="","",M46-L46+1) -> 2 | O46: =IF(L46="","",L46-$S$2+1) -> 15
A47: CT-24 | B47: Walking (stretch) | C47: Sequence controlled falls between edges and corners, re-stabilising after each, to achieve a multi-step directional traverse. | D47: Control & Software | E47: Andrea | F47: Nicc | G47: Verification | H47: P2 | I47: S3 | J47: CT-22 | K47: 2 | N47: =IF(L47="","",M47-L47+1) | O47: =IF(L47="","",L47-$S$2+1) | P47: NOT SCHEDULED - first item to cut
A48: CT-25 | B48: NMPC warm start (stretch) | C48: Explore nonlinear MPC with warm-started IPOPT via CasADi in simulation only, as the future-work section of the report. | D48: Control & Software | E48: Andrea | G48: Software | H48: P2 | J48: CT-14 | K48: 2 | N48: =IF(L48="","",M48-L48+1) | O48: =IF(L48="","",L48-$S$2+1) | P48: NOT SCHEDULED - future work section only
A49: CD-01 | B49: Global layout study | C49: Envelope study in CAD: cube dimension, largest wheel OD the face allows, packaging of three drivers, battery, avionics and perfboard, with the battery centred so the CoM sits at the geometric centre. | D49: CAD Design | E49: Neisa | F49: Suvanna | G49: Design | H49: P0 | I49: S0 | J49: PF-01;PF-09 | K49: 1.5 | L49: 46226 | M49: 46227 | N49: =IF(L49="","",M49-L49+1) -> 2 | O49: =IF(L49="","",L49-$S$2+1) -> 1
A50: CD-02 | B50: Reaction wheel design | C50: Design the reaction wheel to the PF-10 inertia requirement: ~120-130 mm OD, 3-4 mm steel rim, printed hub bolting straight to the motor bell via the M6 mount and bolt circle. Maximise radius, minimise added mass. | D50: CAD Design | E50: Suvanna | F50: Neisa, Dejan | G50: Design | H50: P0 | I50: S1 | J50: PF-10;CD-01 | K50: 1.5 | L50: 46227 | M50: 46229 | N50: =IF(L50="","",M50-L50+1) -> 3 | O50: =IF(L50="","",L50-$S$2+1) -> 2 | P50: Long-lead item, design it FIRST. Buy inertia with radius, not with mass
A51: CD-03 | B51: Motor mount bracket | C51: Design the face bracket that carries all reaction torque into the frame. Design the interface so a machined aluminium part can be substituted without redesigning anything else. | D51: CAD Design | E51: Neisa | G51: Design | H51: P0 | I51: S1 | J51: CD-01 | K51: 1 | L51: 46230 | M51: 46230 | N51: =IF(L51="","",M51-L51+1) -> 1 | O51: =IF(L51="","",L51-$S$2+1) -> 5 | P51: Printed brackets flex - that compliance is an unmodelled resonance that caps control bandwidth
A52: CD-04 | B52: Ring-magnet carrier | C52: Design the carrier that holds the diametrically magnetised ring magnet concentric on the rotating bell. Non-ferrous material. Concentricity error propagates straight into commutation error and torque ripple. | D52: CAD Design | E52: Suvanna | G52: Design | H52: P0 | I52: S1 | J52: CD-02 | K52: 1 | L52: 46230 | M52: 46231 | N52: =IF(L52="","",M52-L52+1) -> 2 | O52: =IF(L52="","",L52-$S$2+1) -> 5 | P52: Precision part
A53: CD-05 | B53: MA600 encoder bracket | C53: Design the bracket that holds the MA600 centred on the magnet's 4 mm thickness with a gap of 0.5 mm or less. Use slotted holes so the gap can be adjusted during assembly. | D53: CAD Design | E53: Neisa | G53: Design | H53: P0 | I53: S1 | J53: CD-04 | K53: 1 | L53: 46231 | M53: 46232 | N53: =IF(L53="","",M53-L53+1) -> 2 | O53: =IF(L53="","",L53-$S$2+1) -> 6 | P53: You will not hit the gap first try - design for adjustment
A54: CD-06 | B54: 1-DoF rig CAD | C54: Design the single-axis test rig: low-friction pivot, motor and wheel mount, IMU mount, counterweight for tuning the equilibrium, and mechanical hard stops to limit travel during failed tuning attempts. | D54: CAD Design | E54: Suvanna | F54: Neisa | G54: Design | H54: P0 | I54: S1 | J54: CD-02;CD-03 | K54: 1 | L54: 46230 | M54: 46231 | N54: =IF(L54="","",M54-L54+1) -> 2 | O54: =IF(L54="","",L54-$S$2+1) -> 5
A55: CD-07 | B55: Tooling & jigs CAD | C55: Design the tooling: knife-edge or arbor wheel-balancing stand, magnet bonding fixture that holds concentricity while adhesive cures, 0.5 mm encoder feeler gauge, and a motor-mount drilling jig for frame orthogonality. | D55: CAD Design | E55: Neisa | G55: Design | H55: P0 | I55: S0 | J55: CD-03 | K55: 1 | L55: 46228 | M55: 46228 | N55: =IF(L55="","",M55-L55+1) -> 1 | O55: =IF(L55="","",L55-$S$2+1) -> 3 | P55: Highest value-per-gram-of-filament on the whole list
A56: CD-08 | B56: moteus board tray | C56: Design the driver mounting tray with standoffs, an airflow gap and cable strain relief. Position it so its SPI cable to the MA600 stays under 20 cm. | D56: CAD Design | E56: Neisa | F56: Pablo | G56: Design | H56: P1 | I56: S2 | J56: CD-01;CD-05 | K56: 0.5 | L56: 46235 | M56: 46235 | N56: =IF(L56="","",M56-L56+1) -> 1 | O56: =IF(L56="","",L56-$S$2+1) -> 10
A57: CD-09 | B57: Avionics tray | C57: Design the tray for the Teensy, CAN-FD adapter and ESP32-C6, keeping the Wi-Fi antenna clear of metal structure and away from the motor phase wiring. | D57: CAD Design | E57: Neisa | F57: Pablo | G57: Design | H57: P1 | I57: S2 | J57: CD-01 | K57: 0.5 | L57: 46235 | M57: 46235 | N57: =IF(L57="","",M57-L57+1) -> 1 | O57: =IF(L57="","",L57-$S$2+1) -> 10
A58: CD-10 | B58: Perfboard mount | C58: Design the mount for the 15 x 9 cm power and signal board, sized to a cube face with clearance for the XT90 entry and the DC-DC module. | D58: CAD Design | E58: Neisa | F58: Pablo | G58: Design | H58: P1 | I58: S2 | J58: CD-01 | K58: 0.25 | L58: 46236 | M58: 46236 | N58: =IF(L58="","",M58-L58+1) -> 1 | O58: =IF(L58="","",L58-$S$2+1) -> 11
A59: CD-11 | B59: Battery cradle | C59: Design a rigid, symmetric, centrally located cradle with strap slots for the 6S pack. A battery that shifts during a jump changes the plant mid-flight. | D59: CAD Design | E59: Suvanna | G59: Design | H59: P0 | I59: S2 | J59: CD-01 | K59: 0.5 | L59: 46234 | M59: 46234 | N59: =IF(L59="","",M59-L59+1) -> 1 | O59: =IF(L59="","",L59-$S$2+1) -> 9 | P59: The battery is ~30% of cube mass - it sets the CoM and the inertia tensor
A60: CD-12 | B60: Frame design | C60: Design the primary structure: three mutually orthogonal motor faces in a closed, torsionally stiff assembly, with corner joints if rod or extrusion based. Verify stiffness by hand before committing to fabrication. | D60: CAD Design | E60: Neisa | F60: Suvanna | G60: Design | H60: P0 | I60: S2 | J60: CD-01;CD-03 | K60: 2 | L60: 46232 | M60: 46234 | N60: =IF(L60="","",M60-L60+1) -> 3 | O60: =IF(L60="","",L60-$S$2+1) -> 7
A61: CD-13 | B61: Wheel burst shields | C61: Design 3 mm or thicker shields over each wheel. They contain a burst and they stop fingers reaching a rim moving at ~47 m/s. | D61: CAD Design | E61: Suvanna | G61: Design | H61: P0 | I61: S2 | J61: CD-02 | K61: 0.5 | L61: 46235 | M61: 46235 | N61: =IF(L61="","",M61-L61+1) -> 1 | O61: =IF(L61="","",L61-$S$2+1) -> 10
A62: CD-14 | B62: Corner caps & edge protectors | C62: Design TPU caps for the eight corners and protectors for the twelve edges. Note that these are the balancing contact surface, so their geometry and compliance enter the plant model. | D62: CAD Design | E62: Suvanna | G62: Design | H62: P1 | I62: S2 | J62: CD-12 | K62: 0.5 | L62: 46236 | M62: 46236 | N62: =IF(L62="","",M62-L62+1) -> 1 | O62: =IF(L62="","",L62-$S$2+1) -> 11
A63: CD-15 | B63: Cable clips | C63: Design clips and strain reliefs that route every cable clear of the rotating wheels. | D63: CAD Design | E63: Suvanna | G63: Design | H63: P1 | I63: S2 | J63: CD-12 | K63: 0.25 | L63: 46236 | M63: 46236 | N63: =IF(L63="","",M63-L63+1) -> 1 | O63: =IF(L63="","",L63-$S$2+1) -> 11 | P63: A cable that snags a spinning wheel ends the project
A64: CD-16 | B64: Brake caliper & linkage | C64: Design the brake: caliper or pawl acting on the wheel rim, plus the servo horn linkage. This is a mechanical-advantage problem - the MG92B gives ~3 kg.cm, so it needs a lever ratio, not a direct push. | D64: CAD Design | E64: Suvanna | F64: Pablo | G64: Design | H64: P1 | I64: S3 | J64: CD-02;PF-10 | K64: 2 | L64: 46240 | M64: 46243 | N64: =IF(L64="","",M64-L64+1) -> 4 | O64: =IF(L64="","",L64-$S$2+1) -> 15
A65: CD-17 | B65: Face panels | C65: Design ribbed face panels that add torsional stiffness and give the demonstrator a finished appearance. | D65: CAD Design | E65: Suvanna | G65: Design | H65: P2 | I65: S2 | J65: CD-12 | K65: 0.5 | L65: 46244 | M65: 46245 | N65: =IF(L65="","",M65-L65+1) -> 2 | O65: =IF(L65="","",L65-$S$2+1) -> 19
A66: CD-18 | B66: Mass properties export | C66: Extract the assembled inertia tensor and CoM location from the CAD model and hand them to the control team as the numbers that replace the PF-09 symbols. | D66: CAD Design | E66: Suvanna | F66: Dejan | G66: Analysis | H66: P0 | I66: S2 | J66: CD-12;CD-11 | K66: 0.5 | L66: 46236 | M66: 46236 | N66: =IF(L66="","",M66-L66+1) -> 1 | O66: =IF(L66="","",L66-$S$2+1) -> 11
A67: CD-19 | B67: CAD freeze v1 | C67: Freeze the design and release the manufacturing package: drawings, DXF for laser cutting, and the print-ready STL set. After this point changes go through a change note. | D67: CAD Design | E67: Neisa | F67: Suvanna | G67: Design | H67: P0 | I67: S2 | J67: CD-03;CD-04;CD-05;CD-08;CD-09;CD-10;CD-11;CD-12;CD-13 | K67: 0.5 | L67: 46237 | M67: 46237 | N67: =IF(L67="","",M67-L67+1) -> 1 | O67: =IF(L67="","",L67-$S$2+1) -> 12
A68: MF-01 | B68: Procurement order | C68: Place the order for everything missing from the BOM: laser-cut steel rims, frame stock, M3 fasteners with heat-set inserts and threadlocker, 3x XT30 pairs, 470-1000 uF / >=50 V low-ESR bus capacitor, E-stop and XT90-S anti-spark connector, 40-60 A fuse, 14 AWG silicone wire, bullet connectors, PETG/TPU/CF-nylon filament, LiPo charger, safe bag and cell alarm, plus one spare motor and one spare moteus. | D68: Manufacturing & Circuits | E68: Pablo | F68: Neisa | G68: Procurement | H68: P0 | I68: S0 | J68: PF-01 | K68: 0.5 | L68: 46226 | M68: 46227 | N68: =IF(L68="","",M68-L68+1) -> 2 | O68: =IF(L68="","",L68-$S$2+1) -> 1 | P68: 3-10 day lead time. This date does NOT move with the document deadline
A69: MF-02 | B69: Bench PSU & safety kit | C69: Secure a current-limited bench supply (0-30 V, >=5 A), set up the test area, and assemble the safety kit: burst shields, eye protection, LiPo-safe storage and charging location. | D69: Manufacturing & Circuits | E69: Pablo | G69: Procurement | H69: P0 | I69: S0 | K69: 0.5 | L69: 46226 | M69: 46227 | N69: =IF(L69="","",M69-L69+1) -> 2 | O69: =IF(L69="","",L69-$S$2+1) -> 1 | P69: A current-limited supply is the difference between a bug and a fire
A70: MF-03 | B70: Bench bring-up (1 axis) | C70: Bring up one motor, one moteus and one MA600 on the bench supply. Set the unique CAN ID first, run moteus_tool calibration and the MA600 bias-current trim, then verify in tview: encoder counts monotonic over a full revolution, commanded current tracks measured, no cogging faults. | D70: Manufacturing & Circuits | E70: Pablo | F70: Nicc | G70: Build | H70: P0 | I70: S1 | J70: MF-02 | K70: 1.5 | L70: 46228 | M70: 46230 | N70: =IF(L70="","",M70-L70+1) -> 3 | O70: =IF(L70="","",L70-$S$2+1) -> 3 | P70: Set CAN IDs before the boards are bussed together or you cannot address them
A71: MF-04 | B71: Print queue A - jigs | C71: Print the tooling from CD-07: balancing arbor, magnet bonding fixture, feeler gauge, drilling jig. These go first because everything downstream depends on them. | D71: Manufacturing & Circuits | E71: Neisa | G71: Build | H71: P0 | I71: S0 | J71: CD-07 | K71: 1 | L71: 46228 | M71: 46229 | N71: =IF(L71="","",M71-L71+1) -> 2 | O71: =IF(L71="","",L71-$S$2+1) -> 3 | P71: The printer is a serial bottleneck - queue order is a scheduling decision
A72: MF-05 | B72: Print queue B - S1 parts | C72: Print the single-axis rig parts: rig frame, motor bracket, wheel hub, magnet carrier, encoder bracket. Expect two or three iterations on the encoder bracket gap. | D72: Manufacturing & Circuits | E72: Neisa | G72: Build | H72: P0 | I72: S1 | J72: CD-06;MF-04 | K72: 1.5 | L72: 46230 | M72: 46231 | N72: =IF(L72="","",M72-L72+1) -> 2 | O72: =IF(L72="","",L72-$S$2+1) -> 5
A73: MF-06 | B73: Fabricate wheels x4 | C73: Fabricate four reaction wheels - three for the cube and one spare so the 1-DoF rig survives cube integration. Cut or receive the rims, print the hubs, bolt them together, bond the ring magnets in the fixture. | D73: Manufacturing & Circuits | E73: Suvanna | F73: Neisa | G73: Build | H73: P0 | I73: S1 | J73: CD-02;MF-01;MF-05 | K73: 2 | L73: 46231 | M73: 46233 | N73: =IF(L73="","",M73-L73+1) -> 3 | O73: =IF(L73="","",L73-$S$2+1) -> 6 | P73: Build FOUR, not three - keep a development bench alive
A74: MF-07 | B74: Balance & spin test | C74: Statically balance every wheel on the arbor, then spin each to full speed inside a containment box behind a shield while logging vibration on the IMU. Rebalance until the vibration floor is acceptable. | D74: Manufacturing & Circuits | E74: Suvanna | F74: Neisa | G74: Verification | H74: P0 | I74: S1 | J74: MF-06;MF-04 | K74: 1 | L74: 46233 | M74: 46234 | N74: =IF(L74="","",M74-L74+1) -> 2 | O74: =IF(L74="","",L74-$S$2+1) -> 8 | P74: 1 g of unbalance at 60 mm and 7000 rpm produces 32 N. Most-skipped step, commonest cause of a noisy filter
A75: MF-08 | B75: Assemble 1-DoF rig | C75: Assemble the rig: motor, balanced wheel, encoder set to the 0.5 mm gap with the feeler gauge, IMU mounted rigidly and aligned, wiring, and mechanical hard stops. | D75: Manufacturing & Circuits | E75: Pablo | F75: Neisa | G75: Build | H75: P0 | I75: S1 | J75: MF-05;MF-07;MF-03 | K75: 1 | L75: 46234 | M75: 46235 | N75: =IF(L75="","",M75-L75+1) -> 2 | O75: =IF(L75="","",L75-$S$2+1) -> 9
A76: MF-09 | B76: Power & signal schematic | C76: Draw the full power and signal schematic before any soldering: bus distribution, DC-DC, decoupling, CAN split termination, connector pinouts, star ground point. | D76: Manufacturing & Circuits | E76: Pablo | G76: Design | H76: P0 | I76: S2 | J76: PF-01 | K76: 0.5 | L76: 46232 | M76: 46232 | N76: =IF(L76="","",M76-L76+1) -> 1 | O76: =IF(L76="","",L76-$S$2+1) -> 7 | P76: An ad-hoc perfboard is undebuggable and will eat two days
A77: MF-10 | B77: Build perfboard | C77: Build the power and signal board: XT90 input, LM2596 set to 5.00 V and verified with a multimeter BEFORE anything is connected, 5 V bulk capacitance, CAN split termination (2x 60.4 ohm plus 4.7 nF) at each bus end, headers for Teensy, adapter, ESP32, IMU and servo, single star ground. | D77: Manufacturing & Circuits | E77: Pablo | G77: Build | H77: P0 | I77: S2 | J77: MF-09;MF-01 | K77: 2 | L77: 46237 | M77: 46239 | N77: =IF(L77="","",M77-L77+1) -> 3 | O77: =IF(L77="","",L77-$S$2+1) -> 12 | P77: The 100 uF caps are 16 V parts - they must never touch the 25.2 V bus
A78: MF-11 | B78: Harness fabrication | C78: Build the harnesses: XT90 to 3x XT30 power distribution, JST-PH3 CAN daisy chain, motor phase leads, inline E-stop and fuse, and a separate 5 V feed for the servo. | D78: Manufacturing & Circuits | E78: Pablo | G78: Build | H78: P0 | I78: S2 | J78: MF-10 | K78: 1 | L78: 46239 | M78: 46240 | N78: =IF(L78="","",M78-L78+1) -> 2 | O78: =IF(L78="","",L78-$S$2+1) -> 14
A79: MF-12 | B79: Print queue C - Tier 1 | C79: Print the structural set: 3x motor bracket, 3x wheel hub, 3x magnet carrier, 3x encoder bracket, 3x moteus tray, avionics tray, battery cradle, frame corner joints. | D79: Manufacturing & Circuits | E79: Neisa | G79: Build | H79: P0 | I79: S2 | J79: CD-19;MF-05 | K79: 2.5 | L79: 46237 | M79: 46240 | N79: =IF(L79="","",M79-L79+1) -> 4 | O79: =IF(L79="","",L79-$S$2+1) -> 12
A80: MF-13 | B80: Fabricate frame | C80: Cut and drill the frame stock using the drilling jig, assemble it, and verify that the three motor faces are mutually orthogonal before anything else is mounted. | D80: Manufacturing & Circuits | E80: Suvanna | F80: Pablo | G80: Build | H80: P0 | I80: S2 | J80: CD-12;MF-01 | K80: 2 | L80: 46237 | M80: 46239 | N80: =IF(L80="","",M80-L80+1) -> 3 | O80: =IF(L80="","",L80-$S$2+1) -> 12
A81: MF-14 | B81: Print queue D - Tier 2 | C81: Print the protective set: 8x TPU corner caps, 12x edge protectors, 3x burst shields, cable clips and strain reliefs. | D81: Manufacturing & Circuits | E81: Suvanna | G81: Build | H81: P1 | I81: S2 | J81: CD-13;CD-14;MF-12 | K81: 1 | L81: 46241 | M81: 46242 | N81: =IF(L81="","",M81-L81+1) -> 2 | O81: =IF(L81="","",L81-$S$2+1) -> 16
A82: MF-15 | B82: Cube integration | C82: Assemble the complete cube: three motor, wheel and encoder assemblies onto the frame, battery centred and strapped, drivers, avionics and perfboard mounted, full harness installed, all cabling clipped clear of the wheels. | D82: Manufacturing & Circuits | E82: Pablo | F82: Neisa, Suvanna | G82: Build | H82: P0 | I82: S2 | J82: MF-12;MF-13;MF-11;MF-07 | K82: 2 | L82: 46241 | M82: 46242 | N82: =IF(L82="","",M82-L82+1) -> 2 | O82: =IF(L82="","",L82-$S$2+1) -> 16
A83: MF-16 | B83: Power-on / smoke test | C83: First power-up on the bench supply, then the battery: confirm all three moteus are addressable on one bus, the IMU streams, telemetry is live, the E-stop cuts power, and the 5 V rail does not brown out when three motors step simultaneously. | D83: Manufacturing & Circuits | E83: Pablo | F83: Nicc | G83: Verification | H83: P0 | I83: S2 | J83: MF-15;CT-05;CT-08 | K83: 1 | L83: 46243 | M83: 46243 | N83: =IF(L83="","",M83-L83+1) -> 1 | O83: =IF(L83="","",L83-$S$2+1) -> 18
A84: MF-17 | B84: Brake mechanism build | C84: Fabricate and fit the brake caliper and servo linkage, then bench-test it on the rig wheel: measure the achieved deceleration and compare it against the PF-10 impulse requirement. | D84: Manufacturing & Circuits | E84: Suvanna | F84: Pablo | G84: Build | H84: P1 | I84: S3 | J84: CD-16;MF-12 | K84: 2 | L84: 46244 | M84: 46247 | N84: =IF(L84="","",M84-L84+1) -> 4 | O84: =IF(L84="","",L84-$S$2+1) -> 19
A85: MF-18 | B85: Rework buffer | C85: Reserved capacity for repairs, reprints, resoldering and replacing whatever breaks. Distributed across the build weeks rather than booked as a block. | D85: Manufacturing & Circuits | E85: Pablo | G85: Build | H85: P1 | K85: 2 | L85: 46237 | M85: 46253 | N85: =IF(L85="","",M85-L85+1) -> 17 | O85: =IF(L85="","",L85-$S$2+1) -> 12 | P85: You will need it
A86: M0 | B86: GATE: Procurement | C86: PASS CRITERION: all open questions answered in writing, and the full MF-01 order confirmed as placed. | D86: Milestone | E86: All | G86: Milestone | H86: P0 | I86: S0 | J86: PF-01;MF-01 | K86: 0 | L86: 46227 | M86: 46227 | N86: =IF(L86="","",M86-L86+1) -> 1 | O86: =IF(L86="","",L86-$S$2+1) -> 2
A87: M0b | B87: GATE: TDD draft body | C87: PASS CRITERION: PF-11a complete internally. Not a submission - this exists purely to stop the 3 August deadline from absorbing build time. | D87: Milestone | E87: All | G87: Milestone | H87: P0 | I87: S0 | J87: PF-11a | K87: 0 | L87: 46229 | M87: 46229 | N87: =IF(L87="","",M87-L87+1) -> 1 | O87: =IF(L87="","",L87-$S$2+1) -> 4
A88: M1 | B88: GATE: Electrical chain | C88: PASS CRITERION: a motor spins under a torque command issued by the Teensy over CAN-FD, and the MA600 reads cleanly and monotonically over a full revolution. | D88: Milestone | E88: All | G88: Milestone | H88: P0 | I88: S1 | J88: MF-03;CT-05;CT-09 | K88: 0 | L88: 46234 | M88: 46234 | N88: =IF(L88="","",M88-L88+1) -> 1 | O88: =IF(L88="","",L88-$S$2+1) -> 9
A89: M2 | B89: GATE: Stage S1 complete | C89: PASS CRITERION: the 1-DoF pendulum balances for at least 60 s and recovers from a finger poke; Kt, J_wheel and friction are measured and tabulated. | D89: Milestone | E89: All | G89: Milestone | H89: P0 | I89: S1 | J89: CT-10;CT-11 | K89: 0 | L89: 46236 | M89: 46236 | N89: =IF(L89="","",M89-L89+1) -> 1 | O89: =IF(L89="","",L89-$S$2+1) -> 11
A90: M3 | B90: GATE: TDD v1 submitted | C90: PASS CRITERION: document delivered, including the S1 experimental results and the measured plant parameters. | D90: Milestone | E90: All | G90: Milestone | H90: P0 | I90: S0 | J90: PF-11c | K90: 0 | L90: 46237 | M90: 46237 | N90: =IF(L90="","",M90-L90+1) -> 1 | O90: =IF(L90="","",L90-$S$2+1) -> 12 | P90: DELIVERABLE
A91: M4 | B91: GATE: Cube integrated | C91: PASS CRITERION: powered cube with all three moteus addressable, IMU streaming, telemetry live, and no brownout under a simultaneous three-motor step. | D91: Milestone | E91: All | G91: Milestone | H91: P0 | I91: S2 | J91: MF-16 | K91: 0 | L91: 46243 | M91: 46243 | N91: =IF(L91="","",M91-L91+1) -> 1 | O91: =IF(L91="","",L91-$S$2+1) -> 18
A92: M5 | B92: GATE: Stage S2a - edge | C92: PASS CRITERION: the cube balances on an edge for at least 60 s and rejects a disturbance. | D92: Milestone | E92: All | G92: Milestone | H92: P0 | I92: S2 | J92: CT-18 | K92: 0 | L92: 46247 | M92: 46247 | N92: =IF(L92="","",M92-L92+1) -> 1 | O92: =IF(L92="","",L92-$S$2+1) -> 22 | P92: If this fails, kill stage S3 the same day and redirect to corner balance plus documentation
A93: M6 | B93: GATE: Stage S2b/c - corner & slew | C93: PASS CRITERION: the cube balances on a corner with pointing accuracy and jitter measured, and completes a commanded slew with a reported settling time. | D93: Milestone | E93: All | G93: Milestone | H93: P0 | I93: S2 | J93: CT-19;CT-20 | K93: 0 | L93: 46250 | M93: 46250 | N93: =IF(L93="","",M93-L93+1) -> 1 | O93: =IF(L93="","",L93-$S$2+1) -> 25
A94: M7 | B94: GATE: Stage S3 - jump | C94: PASS CRITERION: a face-to-edge jump-up executed and captured on slow-motion video. | D94: Milestone | E94: All | G94: Milestone | H94: P1 | I94: S3 | J94: CT-21 | K94: 0 | L94: 46252 | M94: 46252 | N94: =IF(L94="","",M94-L94+1) -> 1 | O94: =IF(L94="","",L94-$S$2+1) -> 27
A95: M8 | B95: GATE: Final delivery | C95: PASS CRITERION: TDD v2, demo video and presentation delivered. | D95: Milestone | E95: All | G95: Milestone | H95: P0 | J95: PF-18;PF-19 | K95: 0 | L95: 46253 | M95: 46253 | N95: =IF(L95="","",M95-L95+1) -> 1 | O95: =IF(L95="","",L95-$S$2+1) -> 28 | P95: DELIVERABLE

Sheet Legend & Assumptions
A1: CUBLI PROJECT - WBS LEGEND & ASSUMPTIONS
A3: COLUMNS
A4: Code | B4: Unique task ID. Prefix = workstream. M-codes are zero-duration milestone gates.
A5: Task Name | B5: Short label - use this one as the Gantt bar label.
A6: Specification | B6: What actually has to be done. This is the working instruction for whoever owns the task.
A7: Effort (person-days) | B7: Work content for ONE person. Not the same as calendar span - parallel work is expected.
A8: Start / Finish | B8: Scheduled calendar dates. Blank = deliberately unscheduled stretch task.
A9: Span (cal. days) | B9: Formula = Finish - Start + 1.
A10: Day # from start | B10: Formula = Start - project start + 1. Use as the X offset for a stacked-bar Gantt.
A11: Predecessors | B11: Semicolon-separated codes that must complete first.
A12: Notes / watch-outs | B12: The failure mode or the reason the task exists. Read before starting the task.
A14: CATEGORY (workstream)
A15: Formulation & Docs | B15: Modelling, derivations, requirements, TDD and final report. Cross-cutting: one owner, everyone contributes.
A16: Control & Software | B16: Control law design, estimation, embedded firmware, telemetry, hardware bring-up tests.
A17: CAD Design | B17: All mechanical design: wheels, brackets, frame, tooling, brake linkage.
A18: Manufacturing & Circuits | B18: Procurement, 3D printing, fabrication, soldering, harnessing, assembly, integration tests.
A19: Milestone | B19: Zero-effort gate. Binary pass/fail, no partial credit.
A21: TYPOLOGY
A22: Analysis | B22: Derivation, calculation, budget.
A23: Design | B23: CAD or schematic design work.
A24: Build | B24: Physical fabrication, printing, assembly, soldering.
A25: Software | B25: Code written on a computer.
A26: Verification | B26: Test on hardware against a stated criterion.
A27: Management | B27: Planning and documentation.
A28: Procurement | B28: Buying or securing equipment.
A30: PRIORITY
A31: P0 | B31: Critical path. Slipping this slips the project end date.
A32: P1 | B32: Important, has float, but a milestone is degraded without it.
A33: P2 | B33: Stretch / nice-to-have. Cut first.
A35: STAGE (prototype)
A36: S0 | B36: Common foundation - applies to all prototypes.
A37: S1 | B37: 1-DoF reaction-wheel inverted pendulum (ETH-style single axis).
A38: S2 | B38: 3D Cubli - edge balance, corner balance, commanded slew.
A39: S3 | B39: Jump-up with the braking system.
A41: ASSUMPTIONS (change these and the schedule changes)
A42: Team size | B42: 4-6 people: one control lead, one CAD lead, one hardware lead, one documentation owner. ASSUMPTION - not confirmed.
A43: Working days | B43: All 7 days per week treated as working days. If weekends are off, ~8 working days are lost and stage S3 is not achievable.
A44: 3D printer | B44: ONE printer, ~40-60 h total, strictly serial. Queue order: jigs > S1 rig > precision encoder/magnet parts > cube structure > TPU protection.
A45: Actuation sets | B45: 3 motors + 3 moteus + 3 MA600 per cube, plus one spare set so the 1-DoF rig survives cube integration. UNCONFIRMED - BOM open question #1.
A46: Cube geometry | B46: 150 mm, ~2.0 kg. Source: cubli_hardware_architecture.md section 5, itself an assumption.
A47: Procurement lead time | B47: 3-10 days on laser-cut steel rims and frame stock. Single largest schedule risk.
A48: Deadlines | B48: Preliminary TDD: Monday 3 August 2026. Final delivery: Wednesday 19 August 2026. Both user-confirmed.
A50: HOW TO BUILD THE GANTT
A51: 1 | B51: Select Task Name (B), Start (L) and Span (N). Insert > Chart > Stacked Bar.
A52: 2 | B52: Series 1 = Start, Series 2 = Span. Set Series 1 fill to No Fill - it becomes the invisible offset.
A53: 3 | B53: Format the vertical axis with 'Categories in reverse order' so the first task sits at the top.
A54: 4 | B54: Set the horizontal axis Minimum to 46226 (23-Jul-2026) and Maximum to 46253 (19-Aug-2026).
A55: 5 | B55: Colour bars by Category (D), or filter column E to chart one person's workload.
A56: 6 | B56: Milestone rows have zero effort and a 1-day span - format them as diamonds or a distinct colour.

Sheet Resource Loading
A1: RESOURCE LOADING - lead-owned effort per person
A2: Counts only tasks where the person is the LEAD. Support effort is real but not counted here, so these are lower bounds. 28 calendar days available (23 Jul - 19 Aug).
A4: Person | B4: Role | C4: Lead tasks | D4: Lead effort | E4: Shared doc share | F4: TOTAL effort | G4: P0 lead effort | H4: Required availability | I4: Assessment
A5: Neisa | B5: CAD & 3D printing | C5: =COUNTIF(WBS!$E$2:$E$95,A5) -> 12 | D5: =SUMIF(WBS!$E$2:$E$95,A5,WBS!$K$2:$K$95) -> 13.25 | E5: =SUMIF(WBS!$E$2:$E$95,"ALL",WBS!$K$2:$K$95)/$B$15 -> 1.4166667 | F5: =D5+E5 -> 14.666667 | G5: =SUMIFS(WBS!$K$2:$K$95,WBS!$E$2:$E$95,A5,WBS!$H$2:$H$95,"P0") -> 12 | H5: =F5/$B$14 -> 0.52380952 | I5: =IF(H5>0.75,"OVERLOADED",IF(H5>0.5,"Heavy",IF(H5>0.3,"Balanced","Has float"))) -> Heavy
A6: Suvanna | B6: CAD & mechanical fab | C6: =COUNTIF(WBS!$E$2:$E$95,A6) -> 15 | D6: =SUMIF(WBS!$E$2:$E$95,A6,WBS!$K$2:$K$95) -> 16.25 | E6: =SUMIF(WBS!$E$2:$E$95,"ALL",WBS!$K$2:$K$95)/$B$15 -> 1.4166667 | F6: =D6+E6 -> 17.666667 | G6: =SUMIFS(WBS!$K$2:$K$95,WBS!$E$2:$E$95,A6,WBS!$H$2:$H$95,"P0") -> 10 | H6: =F6/$B$14 -> 0.63095238 | I6: =IF(H6>0.75,"OVERLOADED",IF(H6>0.5,"Heavy",IF(H6>0.3,"Balanced","Has float"))) -> Heavy
A7: Dejan | B7: Mathematics & formulation (doc owner) | C7: =COUNTIF(WBS!$E$2:$E$95,A7) -> 13 | D7: =SUMIF(WBS!$E$2:$E$95,A7,WBS!$K$2:$K$95) -> 10 | E7: =SUMIF(WBS!$E$2:$E$95,"ALL",WBS!$K$2:$K$95)/$B$15 -> 1.4166667 | F7: =D7+E7 -> 11.416667 | G7: =SUMIFS(WBS!$K$2:$K$95,WBS!$E$2:$E$95,A7,WBS!$H$2:$H$95,"P0") -> 9 | H7: =F7/$B$14 -> 0.4077381 | I7: =IF(H7>0.75,"OVERLOADED",IF(H7>0.5,"Heavy",IF(H7>0.3,"Balanced","Has float"))) -> Balanced
A8: Nicc | B8: Control - firmware & estimation | C8: =COUNTIF(WBS!$E$2:$E$95,A8) -> 12 | D8: =SUMIF(WBS!$E$2:$E$95,A8,WBS!$K$2:$K$95) -> 16 | E8: =SUMIF(WBS!$E$2:$E$95,"ALL",WBS!$K$2:$K$95)/$B$15 -> 1.4166667 | F8: =D8+E8 -> 17.416667 | G8: =SUMIFS(WBS!$K$2:$K$95,WBS!$E$2:$E$95,A8,WBS!$H$2:$H$95,"P0") -> 9.5 | H8: =F8/$B$14 -> 0.62202381 | I8: =IF(H8>0.75,"OVERLOADED",IF(H8>0.5,"Heavy",IF(H8>0.3,"Balanced","Has float"))) -> Heavy
A9: Andrea | B9: Control - control law & simulation | C9: =COUNTIF(WBS!$E$2:$E$95,A9) -> 13 | D9: =SUMIF(WBS!$E$2:$E$95,A9,WBS!$K$2:$K$95) -> 19 | E9: =SUMIF(WBS!$E$2:$E$95,"ALL",WBS!$K$2:$K$95)/$B$15 -> 1.4166667 | F9: =D9+E9 -> 20.416667 | G9: =SUMIFS(WBS!$K$2:$K$95,WBS!$E$2:$E$95,A9,WBS!$H$2:$H$95,"P0") -> 11.5 | H9: =F9/$B$14 -> 0.72916667 | I9: =IF(H9>0.75,"OVERLOADED",IF(H9>0.5,"Heavy",IF(H9>0.3,"Balanced","Has float"))) -> Heavy
A10: Pablo | B10: Circuits, layout & manufacturing | C10: =COUNTIF(WBS!$E$2:$E$95,A10) -> 10 | D10: =SUMIF(WBS!$E$2:$E$95,A10,WBS!$K$2:$K$95) -> 12 | E10: =SUMIF(WBS!$E$2:$E$95,"ALL",WBS!$K$2:$K$95)/$B$15 -> 1.4166667 | F10: =D10+E10 -> 13.416667 | G10: =SUMIFS(WBS!$K$2:$K$95,WBS!$E$2:$E$95,A10,WBS!$H$2:$H$95,"P0") -> 10 | H10: =F10/$B$14 -> 0.47916667 | I10: =IF(H10>0.75,"OVERLOADED",IF(H10>0.5,"Heavy",IF(H10>0.3,"Balanced","Has float"))) -> Balanced
A11: TOTAL | C11: =SUM(C5:C10) -> 75 | D11: =SUM(D5:D10) -> 86.5 | E11: =SUM(E5:E10) -> 8.5 | F11: =SUM(F5:F10) -> 95 | G11: =SUM(G5:G10) -> 62
A13: Calendar days available
B14: 28 | C14: <- edit these two cells
A15: Team size (shared doc divisor) | B15: 6
A16: HOW THE WORK WAS SPLIT
A17: Control (Nicc / Andrea) | B17: Split by function, not by turns. Nicc owns firmware, drivers, estimation and the safety layer; Andrea owns the plant models, LQR design and simulation. They pair on every hardware bring-up task (CT-10, CT-18, CT-19, CT-21) because those are the ones where a second pair of eyes on the telemetry is worth more than a second task being started.
A18: CAD (Neisa / Suvanna) | B18: Neisa owns structure and the parts that feed her own print queue (frame, brackets, trays, CAD freeze). Suvanna owns the precision and long-lead items: reaction wheel, magnet carrier, brake linkage, mass properties. Suvanna also absorbs the wheel fabrication and balancing, which is mechanical work that would otherwise land on Pablo.
A19: Manufacturing (Pablo) | B19: As originally scoped, manufacturing was 25 person-days for one person, on the critical path twice. All four print queues (MF-04, MF-05, MF-12, MF-14) have been reassigned to Neisa, and wheel fabrication, balancing, frame cutting and the brake build to Suvanna. Pablo keeps procurement, bench bring-up, schematic, perfboard, harness, integration and the smoke test - the electrical spine.
A20: Formulation (Dejan) | B20: Dejan is both the mathematician and the document owner, which is the second-heaviest single load in the project. Literature review and the demo video/deck moved to Suvanna, and the risk register to Pablo. The TDD assembly tasks (PF-11a/b/c) must be genuinely co-written - each workstream lead drafts their own section and Dejan integrates, otherwise he becomes the bottleneck in week 2.
A21: Warning | B21: These figures count LEAD effort only. Support time is real and unbudgeted, so treat every 'required availability' percentage as a floor, not a forecast.

Sheet GANTT
A1: CUBLI PROJECT GANTT - 23 July to 19 August 2026
A2: Bars are formula-driven from the WBS sheet: change a Start or Finish there and this chart updates. Colour = workstream. Diamonds = milestone gates.
G3: W1 | H3: W1 | I3: W1 | J3: W1 | K3: W1 | L3: W1 | M3: W1 | N3: W2 | O3: W2 | P3: W2 | Q3: W2 | R3: W2 | S3: W2 | T3: W2 | U3: W3 | V3: W3 | W3: W3 | X3: W3 | Y3: W3 | Z3: W3 | AA3: W3 | AB3: W4 | AC3: W4 | AD3: W4 | AE3: W4 | AF3: W4 | AG3: W4 | AH3: W4
A4: Code | B4: Task Name | C4: Owner | D4: Category | E4: Start | F4: Finish | G4: 46226 | H4: 46227 | I4: 46228 | J4: 46229 | K4: 46230 | L4: 46231 | M4: 46232 | N4: 46233 | O4: 46234 | P4: 46235 | Q4: 46236 | R4: 46237 | S4: 46238 | T4: 46239 | U4: 46240 | V4: 46241 | W4: 46242 | X4: 46243 | Y4: 46244 | Z4: 46245 | AA4: 46246 | AB4: 46247 | AC4: 46248 | AD4: 46249 | AE4: 46250 | AF4: 46251 | AG4: 46252 | AH4: 46253
A5: =WBS!A2 -> PF-01 | B5: =WBS!B2 -> Close open questions | C5: =WBS!E2 -> Dejan | D5: =WBS!D2 -> Formulation & Docs | E5: =WBS!L2 -> 46226 | F5: =WBS!M2 -> 46226 | G5: =IF($E5="","",IF(AND(G$4>=$E5,G$4<=$F5),IF($D5="Milestone","D",1),"")) -> 1 | H5: =IF($E5="","",IF(AND(H$4>=$E5,H$4<=$F5),IF($D5="Milestone","D",1),"")) | I5: =IF($E5="","",IF(AND(I$4>=$E5,I$4<=$F5),IF($D5="Milestone","D",1),"")) | J5: =IF($E5="","",IF(AND(J$4>=$E5,J$4<=$F5),IF($D5="Milestone","D",1),"")) | K5: =IF($E5="","",IF(AND(K$4>=$E5,K$4<=$F5),IF($D5="Milestone","D",1),"")) | L5: =IF($E5="","",IF(AND(L$4>=$E5,L$4<=$F5),IF($D5="Milestone","D",1),"")) | M5: =IF($E5="","",IF(AND(M$4>=$E5,M$4<=$F5),IF($D5="Milestone","D",1),"")) | N5: =IF($E5="","",IF(AND(N$4>=$E5,N$4<=$F5),IF($D5="Milestone","D",1),"")) | ... AH5: =IF($E5="","",IF(AND(AH$4>=$E5,AH$4<=$F5),IF($D5="Milestone","D",1),""))
A6: =WBS!A3 -> PF-02 | B6: =WBS!B3 -> Problem statement & narrative | C6: =WBS!E3 -> Dejan | D6: =WBS!D3 -> Formulation & Docs | E6: =WBS!L3 -> 46226 | F6: =WBS!M3 -> 46226 | G6: =IF($E6="","",IF(AND(G$4>=$E6,G$4<=$F6),IF($D6="Milestone","D",1),"")) -> 1 | H6: =IF($E6="","",IF(AND(H$4>=$E6,H$4<=$F6),IF($D6="Milestone","D",1),"")) | I6: =IF($E6="","",IF(AND(I$4>=$E6,I$4<=$F6),IF($D6="Milestone","D",1),"")) | J6: =IF($E6="","",IF(AND(J$4>=$E6,J$4<=$F6),IF($D6="Milestone","D",1),"")) | K6: =IF($E6="","",IF(AND(K$4>=$E6,K$4<=$F6),IF($D6="Milestone","D",1),"")) | L6: =IF($E6="","",IF(AND(L$4>=$E6,L$4<=$F6),IF($D6="Milestone","D",1),"")) | M6: =IF($E6="","",IF(AND(M$4>=$E6,M$4<=$F6),IF($D6="Milestone","D",1),"")) | N6: =IF($E6="","",IF(AND(N$4>=$E6,N$4<=$F6),IF($D6="Milestone","D",1),"")) | ... AH6: =IF($E6="","",IF(AND(AH$4>=$E6,AH$4<=$F6),IF($D6="Milestone","D",1),""))
A7: =WBS!A4 -> PF-03 | B7: =WBS!B4 -> Scope & requirements | C7: =WBS!E4 -> Dejan | D7: =WBS!D4 -> Formulation & Docs | E7: =WBS!L4 -> 46227 | F7: =WBS!M4 -> 46227 | G7: =IF($E7="","",IF(AND(G$4>=$E7,G$4<=$F7),IF($D7="Milestone","D",1),"")) | H7: =IF($E7="","",IF(AND(H$4>=$E7,H$4<=$F7),IF($D7="Milestone","D",1),"")) -> 1 | I7: =IF($E7="","",IF(AND(I$4>=$E7,I$4<=$F7),IF($D7="Milestone","D",1),"")) | J7: =IF($E7="","",IF(AND(J$4>=$E7,J$4<=$F7),IF($D7="Milestone","D",1),"")) | K7: =IF($E7="","",IF(AND(K$4>=$E7,K$4<=$F7),IF($D7="Milestone","D",1),"")) | L7: =IF($E7="","",IF(AND(L$4>=$E7,L$4<=$F7),IF($D7="Milestone","D",1),"")) | M7: =IF($E7="","",IF(AND(M$4>=$E7,M$4<=$F7),IF($D7="Milestone","D",1),"")) | N7: =IF($E7="","",IF(AND(N$4>=$E7,N$4<=$F7),IF($D7="Milestone","D",1),"")) | ... AH7: =IF($E7="","",IF(AND(AH$4>=$E7,AH$4<=$F7),IF($D7="Milestone","D",1),""))
A8: =WBS!A5 -> PF-04 | B8: =WBS!B5 -> Milestones & staging | C8: =WBS!E5 -> Dejan | D8: =WBS!D5 -> Formulation & Docs | E8: =WBS!L5 -> 46228 | F8: =WBS!M5 -> 46228 | G8: =IF($E8="","",IF(AND(G$4>=$E8,G$4<=$F8),IF($D8="Milestone","D",1),"")) | H8: =IF($E8="","",IF(AND(H$4>=$E8,H$4<=$F8),IF($D8="Milestone","D",1),"")) | I8: =IF($E8="","",IF(AND(I$4>=$E8,I$4<=$F8),IF($D8="Milestone","D",1),"")) -> 1 | J8: =IF($E8="","",IF(AND(J$4>=$E8,J$4<=$F8),IF($D8="Milestone","D",1),"")) | K8: =IF($E8="","",IF(AND(K$4>=$E8,K$4<=$F8),IF($D8="Milestone","D",1),"")) | L8: =IF($E8="","",IF(AND(L$4>=$E8,L$4<=$F8),IF($D8="Milestone","D",1),"")) | M8: =IF($E8="","",IF(AND(M$4>=$E8,M$4<=$F8),IF($D8="Milestone","D",1),"")) | N8: =IF($E8="","",IF(AND(N$4>=$E8,N$4<=$F8),IF($D8="Milestone","D",1),"")) | ... AH8: =IF($E8="","",IF(AND(AH$4>=$E8,AH$4<=$F8),IF($D8="Milestone","D",1),""))
A9: =WBS!A6 -> PF-05 | B9: =WBS!B6 -> Roles & RACI | C9: =WBS!E6 -> Dejan | D9: =WBS!D6 -> Formulation & Docs | E9: =WBS!L6 -> 46226 | F9: =WBS!M6 -> 46226 | G9: =IF($E9="","",IF(AND(G$4>=$E9,G$4<=$F9),IF($D9="Milestone","D",1),"")) -> 1 | H9: =IF($E9="","",IF(AND(H$4>=$E9,H$4<=$F9),IF($D9="Milestone","D",1),"")) | I9: =IF($E9="","",IF(AND(I$4>=$E9,I$4<=$F9),IF($D9="Milestone","D",1),"")) | J9: =IF($E9="","",IF(AND(J$4>=$E9,J$4<=$F9),IF($D9="Milestone","D",1),"")) | K9: =IF($E9="","",IF(AND(K$4>=$E9,K$4<=$F9),IF($D9="Milestone","D",1),"")) | L9: =IF($E9="","",IF(AND(L$4>=$E9,L$4<=$F9),IF($D9="Milestone","D",1),"")) | M9: =IF($E9="","",IF(AND(M$4>=$E9,M$4<=$F9),IF($D9="Milestone","D",1),"")) | N9: =IF($E9="","",IF(AND(N$4>=$E9,N$4<=$F9),IF($D9="Milestone","D",1),"")) | ... AH9: =IF($E9="","",IF(AND(AH$4>=$E9,AH$4<=$F9),IF($D9="Milestone","D",1),""))
A10: =WBS!A7 -> PF-06 | B10: =WBS!B7 -> EoM - 1-DoF pendulum | C10: =WBS!E7 -> Dejan | D10: =WBS!D7 -> Formulation & Docs | E10: =WBS!L7 -> 46227 | F10: =WBS!M7 -> 46228 | G10: =IF($E10="","",IF(AND(G$4>=$E10,G$4<=$F10),IF($D10="Milestone","D",1),"")) | H10: =IF($E10="","",IF(AND(H$4>=$E10,H$4<=$F10),IF($D10="Milestone","D",1),"")) -> 1 | I10: =IF($E10="","",IF(AND(I$4>=$E10,I$4<=$F10),IF($D10="Milestone","D",1),"")) -> 1 | J10: =IF($E10="","",IF(AND(J$4>=$E10,J$4<=$F10),IF($D10="Milestone","D",1),"")) | K10: =IF($E10="","",IF(AND(K$4>=$E10,K$4<=$F10),IF($D10="Milestone","D",1),"")) | L10: =IF($E10="","",IF(AND(L$4>=$E10,L$4<=$F10),IF($D10="Milestone","D",1),"")) | M10: =IF($E10="","",IF(AND(M$4>=$E10,M$4<=$F10),IF($D10="Milestone","D",1),"")) | N10: =IF($E10="","",IF(AND(N$4>=$E10,N$4<=$F10),IF($D10="Milestone","D",1),"")) | ... AH10: =IF($E10="","",IF(AND(AH$4>=$E10,AH$4<=$F10),IF($D10="Milestone","D",1),""))
A11: =WBS!A8 -> PF-07 | B11: =WBS!B8 -> EoM - 3D cube | C11: =WBS!E8 -> Dejan | D11: =WBS!D8 -> Formulation & Docs | E11: =WBS!L8 -> 46230 | F11: =WBS!M8 -> 46231 | G11: =IF($E11="","",IF(AND(G$4>=$E11,G$4<=$F11),IF($D11="Milestone","D",1),"")) | H11: =IF($E11="","",IF(AND(H$4>=$E11,H$4<=$F11),IF($D11="Milestone","D",1),"")) | I11: =IF($E11="","",IF(AND(I$4>=$E11,I$4<=$F11),IF($D11="Milestone","D",1),"")) | J11: =IF($E11="","",IF(AND(J$4>=$E11,J$4<=$F11),IF($D11="Milestone","D",1),"")) | K11: =IF($E11="","",IF(AND(K$4>=$E11,K$4<=$F11),IF($D11="Milestone","D",1),"")) -> 1 | L11: =IF($E11="","",IF(AND(L$4>=$E11,L$4<=$F11),IF($D11="Milestone","D",1),"")) -> 1 | M11: =IF($E11="","",IF(AND(M$4>=$E11,M$4<=$F11),IF($D11="Milestone","D",1),"")) | N11: =IF($E11="","",IF(AND(N$4>=$E11,N$4<=$F11),IF($D11="Milestone","D",1),"")) | ... AH11: =IF($E11="","",IF(AND(AH$4>=$E11,AH$4<=$F11),IF($D11="Milestone","D",1),""))
A12: =WBS!A9 -> PF-08 | B12: =WBS!B9 -> Linearisation & controllability | C12: =WBS!E9 -> Dejan | D12: =WBS!D9 -> Formulation & Docs | E12: =WBS!L9 -> 46232 | F12: =WBS!M9 -> 46232 | G12: =IF($E12="","",IF(AND(G$4>=$E12,G$4<=$F12),IF($D12="Milestone","D",1),"")) | H12: =IF($E12="","",IF(AND(H$4>=$E12,H$4<=$F12),IF($D12="Milestone","D",1),"")) | I12: =IF($E12="","",IF(AND(I$4>=$E12,I$4<=$F12),IF($D12="Milestone","D",1),"")) | J12: =IF($E12="","",IF(AND(J$4>=$E12,J$4<=$F12),IF($D12="Milestone","D",1),"")) | K12: =IF($E12="","",IF(AND(K$4>=$E12,K$4<=$F12),IF($D12="Milestone","D",1),"")) | L12: =IF($E12="","",IF(AND(L$4>=$E12,L$4<=$F12),IF($D12="Milestone","D",1),"")) | M12: =IF($E12="","",IF(AND(M$4>=$E12,M$4<=$F12),IF($D12="Milestone","D",1),"")) -> 1 | N12: =IF($E12="","",IF(AND(N$4>=$E12,N$4<=$F12),IF($D12="Milestone","D",1),"")) | ... AH12: =IF($E12="","",IF(AND(AH$4>=$E12,AH$4<=$F12),IF($D12="Milestone","D",1),""))
A13: =WBS!A10 -> PF-09 | B13: =WBS!B10 -> Mass / inertia / CoM budget | C13: =WBS!E10 -> Dejan | D13: =WBS!D10 -> Formulation & Docs | E13: =WBS!L10 -> 46228 | F13: =WBS!M10 -> 46228 | G13: =IF($E13="","",IF(AND(G$4>=$E13,G$4<=$F13),IF($D13="Milestone","D",1),"")) | H13: =IF($E13="","",IF(AND(H$4>=$E13,H$4<=$F13),IF($D13="Milestone","D",1),"")) | I13: =IF($E13="","",IF(AND(I$4>=$E13,I$4<=$F13),IF($D13="Milestone","D",1),"")) -> 1 | J13: =IF($E13="","",IF(AND(J$4>=$E13,J$4<=$F13),IF($D13="Milestone","D",1),"")) | K13: =IF($E13="","",IF(AND(K$4>=$E13,K$4<=$F13),IF($D13="Milestone","D",1),"")) | L13: =IF($E13="","",IF(AND(L$4>=$E13,L$4<=$F13),IF($D13="Milestone","D",1),"")) | M13: =IF($E13="","",IF(AND(M$4>=$E13,M$4<=$F13),IF($D13="Milestone","D",1),"")) | N13: =IF($E13="","",IF(AND(N$4>=$E13,N$4<=$F13),IF($D13="Milestone","D",1),"")) | ... AH13: =IF($E13="","",IF(AND(AH$4>=$E13,AH$4<=$F13),IF($D13="Milestone","D",1),""))
A14: =WBS!A11 -> PF-10 | B14: =WBS!B11 -> Jump-up analysis | C14: =WBS!E11 -> Dejan | D14: =WBS!D11 -> Formulation & Docs | E14: =WBS!L11 -> 46233 | F14: =WBS!M11 -> 46233 | G14: =IF($E14="","",IF(AND(G$4>=$E14,G$4<=$F14),IF($D14="Milestone","D",1),"")) | H14: =IF($E14="","",IF(AND(H$4>=$E14,H$4<=$F14),IF($D14="Milestone","D",1),"")) | I14: =IF($E14="","",IF(AND(I$4>=$E14,I$4<=$F14),IF($D14="Milestone","D",1),"")) | J14: =IF($E14="","",IF(AND(J$4>=$E14,J$4<=$F14),IF($D14="Milestone","D",1),"")) | K14: =IF($E14="","",IF(AND(K$4>=$E14,K$4<=$F14),IF($D14="Milestone","D",1),"")) | L14: =IF($E14="","",IF(AND(L$4>=$E14,L$4<=$F14),IF($D14="Milestone","D",1),"")) | M14: =IF($E14="","",IF(AND(M$4>=$E14,M$4<=$F14),IF($D14="Milestone","D",1),"")) | N14: =IF($E14="","",IF(AND(N$4>=$E14,N$4<=$F14),IF($D14="Milestone","D",1),"")) -> 1 | ... AH14: =IF($E14="","",IF(AND(AH$4>=$E14,AH$4<=$F14),IF($D14="Milestone","D",1),""))
A15: =WBS!A12 -> PF-11a | B15: =WBS!B12 -> TDD - draft body | C15: =WBS!E12 -> ALL | D15: =WBS!D12 -> Formulation & Docs | E15: =WBS!L12 -> 46228 | F15: =WBS!M12 -> 46229 | G15: =IF($E15="","",IF(AND(G$4>=$E15,G$4<=$F15),IF($D15="Milestone","D",1),"")) | H15: =IF($E15="","",IF(AND(H$4>=$E15,H$4<=$F15),IF($D15="Milestone","D",1),"")) | I15: =IF($E15="","",IF(AND(I$4>=$E15,I$4<=$F15),IF($D15="Milestone","D",1),"")) -> 1 | J15: =IF($E15="","",IF(AND(J$4>=$E15,J$4<=$F15),IF($D15="Milestone","D",1),"")) -> 1 | K15: =IF($E15="","",IF(AND(K$4>=$E15,K$4<=$F15),IF($D15="Milestone","D",1),"")) | L15: =IF($E15="","",IF(AND(L$4>=$E15,L$4<=$F15),IF($D15="Milestone","D",1),"")) | M15: =IF($E15="","",IF(AND(M$4>=$E15,M$4<=$F15),IF($D15="Milestone","D",1),"")) | N15: =IF($E15="","",IF(AND(N$4>=$E15,N$4<=$F15),IF($D15="Milestone","D",1),"")) | ... AH15: =IF($E15="","",IF(AND(AH$4>=$E15,AH$4<=$F15),IF($D15="Milestone","D",1),""))
A16: =WBS!A13 -> PF-11b | B16: =WBS!B13 -> TDD - deepen + S1 data | C16: =WBS!E13 -> ALL | D16: =WBS!D13 -> Formulation & Docs | E16: =WBS!L13 -> 46235 | F16: =WBS!M13 -> 46236 | G16: =IF($E16="","",IF(AND(G$4>=$E16,G$4<=$F16),IF($D16="Milestone","D",1),"")) | H16: =IF($E16="","",IF(AND(H$4>=$E16,H$4<=$F16),IF($D16="Milestone","D",1),"")) | I16: =IF($E16="","",IF(AND(I$4>=$E16,I$4<=$F16),IF($D16="Milestone","D",1),"")) | J16: =IF($E16="","",IF(AND(J$4>=$E16,J$4<=$F16),IF($D16="Milestone","D",1),"")) | K16: =IF($E16="","",IF(AND(K$4>=$E16,K$4<=$F16),IF($D16="Milestone","D",1),"")) | L16: =IF($E16="","",IF(AND(L$4>=$E16,L$4<=$F16),IF($D16="Milestone","D",1),"")) | M16: =IF($E16="","",IF(AND(M$4>=$E16,M$4<=$F16),IF($D16="Milestone","D",1),"")) | N16: =IF($E16="","",IF(AND(N$4>=$E16,N$4<=$F16),IF($D16="Milestone","D",1),"")) | ... AH16: =IF($E16="","",IF(AND(AH$4>=$E16,AH$4<=$F16),IF($D16="Milestone","D",1),""))
... A98: =WBS!A95 -> M8 | B98: =WBS!B95 -> GATE: Final delivery | C98: =WBS!E95 -> All | D98: =WBS!D95 -> Milestone | E98: =WBS!L95 -> 46253 | F98: =WBS!M95 -> 46253 | G98: =IF($E98="","",IF(AND(G$4>=$E98,G$4<=$F98),IF($D98="Milestone","D",1),"")) | H98: =IF($E98="","",IF(AND(H$4>=$E98,H$4<=$F98),IF($D98="Milestone","D",1),"")) | I98: =IF($E98="","",IF(AND(I$4>=$E98,I$4<=$F98),IF($D98="Milestone","D",1),"")) | J98: =IF($E98="","",IF(AND(J$4>=$E98,J$4<=$F98),IF($D98="Milestone","D",1),"")) | K98: =IF($E98="","",IF(AND(K$4>=$E98,K$4<=$F98),IF($D98="Milestone","D",1),"")) | L98: =IF($E98="","",IF(AND(L$4>=$E98,L$4<=$F98),IF($D98="Milestone","D",1),"")) | M98: =IF($E98="","",IF(AND(M$4>=$E98,M$4<=$F98),IF($D98="Milestone","D",1),"")) | N98: =IF($E98="","",IF(AND(N$4>=$E98,N$4<=$F98),IF($D98="Milestone","D",1),"")) | ... AH98: =IF($E98="","",IF(AND(AH$4>=$E98,AH$4<=$F98),IF($D98="Milestone","D",1),"")) -> D
A101: LEGEND
B102: Formulation & Docs
B103: Control & Software
B104: CAD Design
B105: Manufacturing & Circuits
A106: D | B106: Milestone gate
A108: Grey columns are weekends. NOTE: this plan treats them as working days.

Sheet Gantt Chart
A1: Classic stacked-bar Gantt (same data, chart form)
A2: Series 1 is the invisible offset (Start), series 2 is the bar (Span). Right-click a bar > Format Data Series to recolour by workstream.
